pythondraw/__init__.py
pythondraw-1.2.2.dist-info/METADATA
pythondraw-1.2.2.dist-info/WHEEL
pythondraw-1.2.2.dist-info/top_level.txt
pythondraw-1.2.2.dist-info/RECORD
