Metadata-Version: 2.1
Name: pythondraw
Version: 1.2.2
Summary: A drawing module more suitable for novices
Home-page: https://xiaodong.indouyin.cn/python/modules/pythondraw/index.html
Author: DY_XiaoDong
Author-email: xiaodong@indouyin.cn
License: MIT
Platform: UNKNOWN
Requires: turtle
